widgets/__init__.py
widgets/ttkb_validators.py
widgets/ttkb_widgets.py
ttkbwidgets-1.0.4.dist-info/AUTHORS.txt
ttkbwidgets-1.0.4.dist-info/LICENSE.txt
ttkbwidgets-1.0.4.dist-info/METADATA
ttkbwidgets-1.0.4.dist-info/WHEEL
ttkbwidgets-1.0.4.dist-info/top_level.txt
ttkbwidgets-1.0.4.dist-info/RECORD
